gns3_mcp/__init__.py
gns3_mcp/cli.py
gns3_mcp/py.typed
gns3_mcp/server/__init__.py
gns3_mcp/server/batch_models.py
gns3_mcp/server/console_manager.py
gns3_mcp/server/error_utils.py
gns3_mcp/server/exceptions.py
gns3_mcp/server/export_tools.py
gns3_mcp/server/gns3_client.py
gns3_mcp/server/link_validator.py
gns3_mcp/server/main.py
gns3_mcp/server/models.py
gns3_mcp/server/prompts/__init__.py
gns3_mcp/server/prompts/lab_setup.py
gns3_mcp/server/prompts/node_setup.py
gns3_mcp/server/prompts/ssh_setup.py
gns3_mcp/server/prompts/topology_discovery.py
gns3_mcp/server/prompts/troubleshooting.py
gns3_mcp/server/resources/__init__.py
gns3_mcp/server/resources/project_resources.py
gns3_mcp/server/resources/resource_manager.py
gns3_mcp/server/resources/session_resources.py
gns3_mcp/server/tools/__init__.py
gns3_mcp/server/tools/console_tools.py
gns3_mcp/server/tools/drawing_tools.py
gns3_mcp/server/tools/link_tools.py
gns3_mcp/server/tools/node_tools.py
gns3_mcp/server/tools/project_tools.py
gns3_mcp/server/tools/resource_tools.py
gns3_mcp/server/tools/ssh_tools.py
gns3_mcp/server/tools/template_tools.py
gns3_mcp-0.46.4.dist-info/licenses/LICENSE
gns3_mcp-0.46.4.dist-info/METADATA
gns3_mcp-0.46.4.dist-info/WHEEL
gns3_mcp-0.46.4.dist-info/entry_points.txt
gns3_mcp-0.46.4.dist-info/top_level.txt
gns3_mcp-0.46.4.dist-info/RECORD
