Metadata-Version: 2.4
Name: gns3-mcp
Version: 0.46.4
Summary: GNS3 lab automation MCP server with AI agent integration
Author-email: Sergei Chistokhin <Sergei@Chistokhin.com>
License-Expression: MIT
Project-URL: Homepage, https://github.com/ChistokhinSV/gns3-mcp
Project-URL: Documentation, https://github.com/ChistokhinSV/gns3-mcp#readme
Project-URL: Repository, https://github.com/ChistokhinSV/gns3-mcp
Project-URL: Issues, https://github.com/ChistokhinSV/gns3-mcp/issues
Project-URL: Changelog, https://github.com/ChistokhinSV/gns3-mcp/blob/master/CHANGELOG.md
Keywords: gns3,mcp,network,automation,ai,claude,fastmcp
Classifier: Development Status :: 4 - Beta
Classifier: Intended Audience :: Developers
Classifier: Intended Audience :: System Administrators
Classifier: Programming Language :: Python :: 3
Classifier: Programming Language :: Python :: 3.10
Classifier: Programming Language :: Python :: 3.11
Classifier: Programming Language :: Python :: 3.12
Classifier: Topic :: System :: Networking
Classifier: Topic :: Software Development :: Libraries :: Python Modules
Classifier: Operating System :: OS Independent
Requires-Python: >=3.10
License-File: LICENSE
Requires-Dist: fastmcp>=2.13.0.2
Requires-Dist: fastapi>=0.115.0
Requires-Dist: httpx>=0.28.1
Requires-Dist: telnetlib3>=2.0.8
Requires-Dist: pydantic>=2.12.3
Requires-Dist: python-dotenv>=1.2.1
Requires-Dist: cairosvg>=2.8.2
Requires-Dist: docker>=7.1.0
Requires-Dist: tabulate>=0.9.0
Provides-Extra: dev
Requires-Dist: pytest>=8.4.2; extra == "dev"
Requires-Dist: pytest-asyncio>=1.2.0; extra == "dev"
Requires-Dist: pytest-mock>=3.15.1; extra == "dev"
Requires-Dist: pytest-cov>=7.0.0; extra == "dev"
Requires-Dist: ruff>=0.14.2; extra == "dev"
Requires-Dist: mypy>=1.18.2; extra == "dev"
Requires-Dist: black>=25.9.0; extra == "dev"
Requires-Dist: pre-commit>=4.3.0; extra == "dev"
Provides-Extra: http
Requires-Dist: uvicorn>=0.30.0; extra == "http"
Dynamic: license-file
